klrrr/__init__.py
klrrr/klrrr.py
klrrr-0.1.dist-info/METADATA
klrrr-0.1.dist-info/WHEEL
klrrr-0.1.dist-info/top_level.txt
klrrr-0.1.dist-info/RECORD
